fast_hangeul_jamo/__init__.py
fast_hangeul_jamo/py.typed
fast_hangeul_jamo-0.1.1.dist-info/WHEEL
fast_hangeul_jamo-0.1.1.dist-info/METADATA
fast_hangeul_jamo-0.1.1.dist-info/RECORD
