Metadata-Version: 2.3
Name: fast-hangeul-jamo
Version: 0.1.1
Summary: Fastest Korean Hangul syllable and jamo manipulation library (meta-package)
Keywords: korean,hangul,jamo,nlp,korean-language
Author: hangeul-jamo contributors
Classifier: Development Status :: 5 - Production/Stable
Classifier: Intended Audience :: Developers
Classifier: License :: OSI Approved :: MIT License
Classifier: Programming Language :: Python :: 3
Classifier: Programming Language :: Python :: 3.13
Classifier: Topic :: Text Processing :: Linguistic
Classifier: Typing :: Typed
Requires-Dist: hangeul-jamo-py>=0.1.0
Requires-Dist: hangeul-jamo-rs>=0.1.1 ; extra == 'rust'
Requires-Python: >=3.13
Project-URL: Repository, https://github.com/gembleman/fast_hangeul_jamo
Provides-Extra: rust
